{
  "Coins": [
    {
      "Exchange": "LBank",
      "ForeignName": "ACA_USDT",
      "Ignore": false,
      "Symbol": "ACA"
    },
    {
      "Exchange": "LBank",
      "ForeignName": "ANKR_USDT",
      "Ignore": false,
      "Symbol": "ANKR"
    },
    {
      "Exchange": "LBank",
      "ForeignName": "METIS_USDT",
      "Ignore": false,
      "Symbol": "METIS"
    },
    {
      "Exchange": "LBank",
      "ForeignName": "AAA_BTC",
      "Ignore": false,
      "Symbol": "AAA"
    },
    {
      "Exchange": "LBank",
      "ForeignName": "AAC_ETH",
      "Ignore": false,
      "Symbol": "AAC"
    },
    {
      "Exchange": "LBank",
      "ForeignName": "AAC_QTUM",
      "Ignore": false,
      "Symbol": "AAC"
    },
    {
      "Exchange": "LBank",
      "ForeignName": "ABT_BTC",
      "Ignore": false,
      "Symbol": "ABT"
    },
    {
      "Exchange": "LBank",
      "ForeignName": "ABT_ETH",
      "Ignore": false,
      "Symbol": "ABT"
    },
    {
      "Exchange": "LBank",
      "ForeignName": "ALI_ETH",
      "Ignore": false,
      "Symbol": "ALI"
    },
    {
      "Exchange": "LBank",
      "ForeignName": "AMO_ETH",
      "Ignore": false,
      "Symbol": "AMO"
    },
    {
      "Exchange": "LBank",
      "ForeignName": "AXS_USDT",
      "Ignore": false,
      "Symbol": "AXS"
    },
    {
      "Exchange": "LBank",
      "ForeignName": "BCH_BTC",
      "Ignore": false,
      "Symbol": "BCH"
    },
    {
      "Exchange": "LBank",
      "ForeignName": "BCH_ETH",
      "Ignore": false,
      "Symbol": "BCH"
    },
    {
      "Exchange": "LBank",
      "ForeignName": "BCH_USDT",
      "Ignore": false,
      "Symbol": "BCH"
    },
    {
      "Exchange": "LBank",
      "ForeignName": "BNB_USDT",
      "Ignore": false,
      "Symbol": "BNB"
    },
    {
      "Exchange": "LBank",
      "ForeignName": "BOSON_USDT",
      "Ignore": false,
      "Symbol": "BOSON"
    },
    {
      "Exchange": "LBank",
      "ForeignName": "BOT_QTUM",
      "Ignore": false,
      "Symbol": "BOT"
    },
    {
      "Exchange": "LBank",
      "ForeignName": "BTC_LBCN",
      "Ignore": false,
      "Symbol": "BTC"
    },
    {
      "Exchange": "LBank",
      "ForeignName": "BTC_TUSD",
      "Ignore": false,
      "Symbol": "BTC"
    },
    {
      "Exchange": "LBank",
      "ForeignName": "BTC_USDT",
      "Ignore": false,
      "Symbol": "BTC"
    },
    {
      "Exchange": "LBank",
      "ForeignName": "BTO_ETH",
      "Ignore": false,
      "Symbol": "BTO"
    },
    {
      "Exchange": "LBank",
      "ForeignName": "BTS_BTC",
      "Ignore": false,
      "Symbol": "BTS"
    },
    {
      "Exchange": "LBank",
      "ForeignName": "BTS_ETH",
      "Ignore": false,
      "Symbol": "BTS"
    },
    {
      "Exchange": "LBank",
      "ForeignName": "BUSD_USDT",
      "Ignore": false,
      "Symbol": "BUSD"
    },
    {
      "Exchange": "LBank",
      "ForeignName": "CDC_ETH",
      "Ignore": false,
      "Symbol": "CDC"
    },
    {
      "Exchange": "LBank",
      "ForeignName": "CHAT_QTUM",
      "Ignore": false,
      "Symbol": "CHAT"
    },
    {
      "Exchange": "LBank",
      "ForeignName": "CPX_BTC",
      "Ignore": false,
      "Symbol": "CPX"
    },
    {
      "Exchange": "LBank",
      "ForeignName": "CPX_ETH",
      "Ignore": false,
      "Symbol": "CPX"
    },
    {
      "Exchange": "LBank",
      "ForeignName": "CS_ETH",
      "Ignore": false,
      "Symbol": "CS"
    },
    {
      "Exchange": "LBank",
      "ForeignName": "DASH_BTC",
      "Ignore": false,
      "Symbol": "DASH"
    },
    {
      "Exchange": "LBank",
      "ForeignName": "DAX_BTC",
      "Ignore": false,
      "Symbol": "DAX"
    },
    {
      "Exchange": "LBank",
      "ForeignName": "DAX_ETH",
      "Ignore": false,
      "Symbol": "DAX"
    },
    {
      "Exchange": "LBank",
      "ForeignName": "DBC_ETH",
      "Ignore": false,
      "Symbol": "DBC"
    },
    {
      "Exchange": "LBank",
      "ForeignName": "DCT_ETH",
      "Ignore": false,
      "Symbol": "DCT"
    },
    {
      "Exchange": "LBank",
      "ForeignName": "DDD_ETH",
      "Ignore": false,
      "Symbol": "DDD"
    },
    {
      "Exchange": "LBank",
      "ForeignName": "DOT_USDT",
      "Ignore": false,
      "Symbol": "DOT"
    },
    {
      "Exchange": "LBank",
      "ForeignName": "EKO_ETH",
      "Ignore": false,
      "Symbol": "EKO"
    },
    {
      "Exchange": "LBank",
      "ForeignName": "ELA_ETH",
      "Ignore": false,
      "Symbol": "ELA"
    },
    {
      "Exchange": "LBank",
      "ForeignName": "EOS_ETH",
      "Ignore": false,
      "Symbol": "EOS"
    },
    {
      "Exchange": "LBank",
      "ForeignName": "ETC_BTC",
      "Ignore": false,
      "Symbol": "ETC"
    },
    {
      "Exchange": "LBank",
      "ForeignName": "ETC_USDT",
      "Ignore": false,
      "Symbol": "ETC"
    },
    {
      "Exchange": "LBank",
      "ForeignName": "ETH_BTC",
      "Ignore": false,
      "Symbol": "ETH"
    },
    {
      "Exchange": "LBank",
      "ForeignName": "ETH_LBCN",
      "Ignore": false,
      "Symbol": "ETH"
    },
    {
      "Exchange": "LBank",
      "ForeignName": "ETH_TUSD",
      "Ignore": false,
      "Symbol": "ETH"
    },
    {
      "Exchange": "LBank",
      "ForeignName": "ETH_USDT",
      "Ignore": false,
      "Symbol": "ETH"
    },
    {
      "Exchange": "LBank",
      "ForeignName": "EXT_ETH",
      "Ignore": false,
      "Symbol": "EXT"
    },
    {
      "Exchange": "LBank",
      "ForeignName": "GUSD_BTC",
      "Ignore": false,
      "Symbol": "GUSD"
    },
    {
      "Exchange": "LBank",
      "ForeignName": "HER_ETH",
      "Ignore": false,
      "Symbol": "HER"
    },
    {
      "Exchange": "LBank",
      "ForeignName": "HT_USDT",
      "Ignore": false,
      "Symbol": "HT"
    },
    {
      "Exchange": "LBank",
      "ForeignName": "IHT_ETH",
      "Ignore": false,
      "Symbol": "IHT"
    },
    {
      "Exchange": "LBank",
      "ForeignName": "IIC_ETH",
      "Ignore": false,
      "Symbol": "IIC"
    },
    {
      "Exchange": "LBank",
      "ForeignName": "ILV_USDT",
      "Ignore": false,
      "Symbol": "ILV"
    },
    {
      "Exchange": "LBank",
      "ForeignName": "INC_ETH",
      "Ignore": false,
      "Symbol": "INC"
    },
    {
      "Exchange": "LBank",
      "ForeignName": "INK_ETH",
      "Ignore": false,
      "Symbol": "INK"
    },
    {
      "Exchange": "LBank",
      "ForeignName": "INK_QTUM",
      "Ignore": false,
      "Symbol": "INK"
    },
    {
      "Exchange": "LBank",
      "ForeignName": "KSM_USDT",
      "Ignore": false,
      "Symbol": "KSM"
    },
    {
      "Exchange": "LBank",
      "ForeignName": "LTC_BTC",
      "Ignore": false,
      "Symbol": "LTC"
    },
    {
      "Exchange": "LBank",
      "ForeignName": "LUNA_USDT",
      "Ignore": false,
      "Symbol": "LUNA"
    },
    {
      "Exchange": "LBank",
      "ForeignName": "MAN_ETH",
      "Ignore": false,
      "Symbol": "MAN"
    },
    {
      "Exchange": "LBank",
      "ForeignName": "MDA_ETH",
      "Ignore": false,
      "Symbol": "MDA"
    },
    {
      "Exchange": "LBank",
      "ForeignName": "MITH_ETH",
      "Ignore": false,
      "Symbol": "MITH"
    },
    {
      "Exchange": "LBank",
      "ForeignName": "MITH_QTUM",
      "Ignore": false,
      "Symbol": "MITH"
    },
    {
      "Exchange": "LBank",
      "ForeignName": "NAS_ETH",
      "Ignore": false,
      "Symbol": "NAS"
    },
    {
      "Exchange": "LBank",
      "ForeignName": "NEO_BTC",
      "Ignore": false,
      "Symbol": "NEO"
    },
    {
      "Exchange": "LBank",
      "ForeignName": "NEO_USDT",
      "Ignore": false,
      "Symbol": "NEO"
    },
    {
      "Exchange": "LBank",
      "ForeignName": "OCN_ETH",
      "Ignore": false,
      "Symbol": "OCN"
    },
    {
      "Exchange": "LBank",
      "ForeignName": "PCH_BTC",
      "Ignore": false,
      "Symbol": "PCH"
    },
    {
      "Exchange": "LBank",
      "ForeignName": "PCH_ETH",
      "Ignore": false,
      "Symbol": "PCH"
    },
    {
      "Exchange": "LBank",
      "ForeignName": "PCH_USDT",
      "Ignore": false,
      "Symbol": "PCH"
    },
    {
      "Exchange": "LBank",
      "ForeignName": "PNT_BTC",
      "Ignore": false,
      "Symbol": "PNT"
    },
    {
      "Exchange": "LBank",
      "ForeignName": "PNT_ETH",
      "Ignore": false,
      "Symbol": "PNT"
    },
    {
      "Exchange": "LBank",
      "ForeignName": "PST_ETH",
      "Ignore": false,
      "Symbol": "PST"
    },
    {
      "Exchange": "LBank",
      "ForeignName": "PTT_ETH",
      "Ignore": false,
      "Symbol": "PTT"
    },
    {
      "Exchange": "LBank",
      "ForeignName": "QTUM_BTC",
      "Ignore": false,
      "Symbol": "QTUM"
    },
    {
      "Exchange": "LBank",
      "ForeignName": "QTUM_ETH",
      "Ignore": false,
      "Symbol": "QTUM"
    },
    {
      "Exchange": "LBank",
      "ForeignName": "QTUM_USDT",
      "Ignore": false,
      "Symbol": "QTUM"
    },
    {
      "Exchange": "LBank",
      "ForeignName": "RAY_USDT",
      "Ignore": false,
      "Symbol": "RAY"
    },
    {
      "Exchange": "LBank",
      "ForeignName": "SAMO_USDT",
      "Ignore": false,
      "Symbol": "SAMO"
    },
    {
      "Exchange": "LBank",
      "ForeignName": "SC_BTC",
      "Ignore": false,
      "Symbol": "SC"
    },
    {
      "Exchange": "LBank",
      "ForeignName": "SKM_ETH",
      "Ignore": false,
      "Symbol": "SKM"
    },
    {
      "Exchange": "LBank",
      "ForeignName": "SSC_ETH",
      "Ignore": false,
      "Symbol": "SSC"
    },
    {
      "Exchange": "LBank",
      "ForeignName": "TAC_ETH",
      "Ignore": false,
      "Symbol": "TAC"
    },
    {
      "Exchange": "LBank",
      "ForeignName": "TEN_USDT",
      "Ignore": false,
      "Symbol": "TEN"
    },
    {
      "Exchange": "LBank",
      "ForeignName": "TKY_ETH",
      "Ignore": false,
      "Symbol": "TKY"
    },
    {
      "Exchange": "LBank",
      "ForeignName": "TNS_BTC",
      "Ignore": false,
      "Symbol": "TNS"
    },
    {
      "Exchange": "LBank",
      "ForeignName": "TNS_LBCN",
      "Ignore": false,
      "Symbol": "TNS"
    },
    {
      "Exchange": "LBank",
      "ForeignName": "TRX_ETH",
      "Ignore": false,
      "Symbol": "TRX"
    },
    {
      "Exchange": "LBank",
      "ForeignName": "UBEX_BTC",
      "Ignore": false,
      "Symbol": "UBEX"
    },
    {
      "Exchange": "LBank",
      "ForeignName": "UBEX_USDT",
      "Ignore": false,
      "Symbol": "UBEX"
    },
    {
      "Exchange": "LBank",
      "ForeignName": "UIP_ETH",
      "Ignore": false,
      "Symbol": "UIP"
    },
    {
      "Exchange": "LBank",
      "ForeignName": "UPS_USDT",
      "Ignore": false,
      "Symbol": "UPS"
    },
    {
      "Exchange": "LBank",
      "ForeignName": "USDT_LBCN",
      "Ignore": false,
      "Symbol": "USDT"
    },
    {
      "Exchange": "LBank",
      "ForeignName": "USDT_TUSD",
      "Ignore": false,
      "Symbol": "USDT"
    },
    {
      "Exchange": "LBank",
      "ForeignName": "UT_ETH",
      "Ignore": false,
      "Symbol": "UT"
    },
    {
      "Exchange": "LBank",
      "ForeignName": "VTHO_BTC",
      "Ignore": false,
      "Symbol": "VTHO"
    },
    {
      "Exchange": "LBank",
      "ForeignName": "VTHO_ETH",
      "Ignore": false,
      "Symbol": "VTHO"
    },
    {
      "Exchange": "LBank",
      "ForeignName": "WICC_ETH",
      "Ignore": false,
      "Symbol": "WICC"
    },
    {
      "Exchange": "LBank",
      "ForeignName": "XWC_BTC",
      "Ignore": false,
      "Symbol": "XWC"
    },
    {
      "Exchange": "LBank",
      "ForeignName": "XWC_ETH",
      "Ignore": false,
      "Symbol": "XWC"
    },
    {
      "Exchange": "LBank",
      "ForeignName": "ZEC_BTC",
      "Ignore": false,
      "Symbol": "ZEC"
    },
    {
      "Exchange": "LBank",
      "ForeignName": "ZEC_ETH",
      "Ignore": false,
      "Symbol": "ZEC"
    },
    {
      "Exchange": "LBank",
      "ForeignName": "ZEC_USDT",
      "Ignore": false,
      "Symbol": "ZEC"
    },
    {
      "Exchange": "LBank",
      "ForeignName": "ZPT_ETH",
      "Ignore": false,
      "Symbol": "ZPT"
    },
    {
      "Exchange": "LBank",
      "ForeignName": "ZSC_ETH",
      "Ignore": false,
      "Symbol": "ZSC"
    }
  ]
}
