{
    "Tokens": [
        {
            "Symbol": "ANKR",
            "Exchange": "HitBTC",
            "Blockchain": "Ethereum",
            "Address": "0x8290333ceF9e6D528dD5618Fb97a76f268f3EDD4"
        },
        {
            "Symbol": "PAR",
            "Exchange": "HitBTC",
            "Blockchain": "Ethereum",
            "Address": "0x68037790A0229e9Ce6EaA8A99ea92964106C4703"
        },
        {
            "Symbol": "MIMO",
            "Exchange": "HitBTC",
            "Blockchain": "Ethereum",
            "Address": "0x90B831fa3Bebf58E9744A14D638E25B4eE06f9Bc"
        },
        {
            "Symbol": "ACAT",
            "Exchange": "HitBTC",
            "Blockchain": "Neo",
            "Address": "7f86d61ff377f1b12e589a5907152b57e2ad9a7a"
        },
        {
            "Symbol": "AE",
            "Exchange": "HitBTC",
            "Blockchain": "Aeternity",
            "Address": "0x0000000000000000000000000000000000000000"
        },
        {
            "Symbol": "AMB",
            "Exchange": "HitBTC",
            "Blockchain": "Ambrosus",
            "Address": "0x0000000000000000000000000000000000000000"
        },
        {
            "Symbol": "ANT",
            "Exchange": "HitBTC",
            "Blockchain": "Ethereum",
            "Address": "0xa117000000f279D81A1D3cc75430fAA017FA5A2e"
        },
        {
            "Symbol": "APPC",
            "Exchange": "HitBTC",
            "Blockchain": "Ethereum",
            "Address": "0x1a7a8BD9106F2B8D977E08582DC7d24c723ab0DB"
        },
        {
            "Symbol": "ARK",
            "Exchange": "HitBTC",
            "Blockchain": "Ark",
            "Address": "0x0000000000000000000000000000000000000000"
        },
        {
            "Symbol": "ART",
            "Exchange": "HitBTC",
            "Blockchain": "Ethereum",
            "Address": "0xfec0cF7fE078a500abf15F1284958F22049c2C7e"
        },
        {
            "Symbol": "AUC",
            "Exchange": "HitBTC",
            "Blockchain": "Ethereum",
            "Address": "0xc12d099be31567add4e4e4d0D45691C3F58f5663"
        },
        {
            "Symbol": "AVT",
            "Exchange": "HitBTC",
            "Blockchain": "Ethereum",
            "Address": "0x0d88eD6E74bbFD96B831231638b66C05571e824F"
        },
        {
            "Symbol": "AXPR",
            "Exchange": "HitBTC",
            "Blockchain": "Ethereum",
            "Address": "0xdD0020B1D5Ba47A54E2EB16800D73Beb6546f91A"
        },
        {
            "Symbol": "BANCA",
            "Exchange": "HitBTC",
            "Blockchain": "Ethereum",
            "Address": "0x998b3B82bC9dBA173990Be7afb772788B5aCB8Bd"
        },
        {
            "Symbol": "BDG",
            "Exchange": "HitBTC",
            "Blockchain": "Ethereum",
            "Address": "0x1961B3331969eD52770751fC718ef530838b6dEE"
        },
        {
            "Symbol": "BERRY",
            "Exchange": "HitBTC",
            "Blockchain": "Ethereum",
            "Address": "0x6aEB95F06CDA84cA345c2dE0F3B7f96923a44f4c"
        },
        {
            "Symbol": "BMC",
            "Exchange": "HitBTC",
            "Blockchain": "Ethereum",
            "Address": "0xDf6Ef343350780BF8C3410BF062e0C015B1DD671"
        },
        {
            "Symbol": "BMH",
            "Exchange": "HitBTC",
            "Blockchain": "Ethereum",
            "Address": "0xF03045a4C8077e38f3B8e2Ed33b8aEE69edF869F"
        },
        {
            "Symbol": "BNB",
            "Exchange": "HitBTC",
            "Blockchain": "BinanceSmartChain",
            "Address": "0x0000000000000000000000000000000000000000"
        },
        {
            "Symbol": "BNK",
            "Exchange": "HitBTC",
            "Blockchain": "Ethereum",
            "Address": "0xC80c5E40220172B36aDee2c951f26F2a577810C5"
        },
        {
            "Symbol": "BOX",
            "Exchange": "HitBTC",
            "Blockchain": "Ethereum",
            "Address": "0xe1A178B681BD05964d3e3Ed33AE731577d9d96dD"
        },
        {
            "Symbol": "BTS",
            "Exchange": "HitBTC",
            "Blockchain": "BitShares",
            "Address": "0x0000000000000000000000000000000000000000"
        },
        {
            "Symbol": "C20",
            "Exchange": "HitBTC",
            "Blockchain": "Ethereum",
            "Address": "0x26E75307Fc0C021472fEb8F727839531F112f317"
        },
        {
            "Symbol": "CDT",
            "Exchange": "HitBTC",
            "Blockchain": "Ethereum",
            "Address": "0x177d39AC676ED1C67A2b268AD7F1E58826E5B0af"
        },
        {
            "Symbol": "CHAT",
            "Exchange": "HitBTC",
            "Blockchain": "Ethereum",
            "Address": "0x442Bc47357919446eAbC18C7211E57a13d983469"
        },
        {
            "Symbol": "CHP",
            "Exchange": "HitBTC",
            "Blockchain": "Ethereum",
            "Address": "0xf3db7560E820834658B590C96234c333Cd3D5E5e"
        },
        {
            "Symbol": "CND",
            "Exchange": "HitBTC",
            "Blockchain": "Ethereum",
            "Address": "0xd4c435F5B09F855C3317c8524Cb1F586E42795fa"
        },
        {
            "Symbol": "COMP",
            "Exchange": "HitBTC",
            "Blockchain": "Ethereum",
            "Address": "0xc00e94Cb662C3520282E6f5717214004A7f26888"
        },
        {
            "Symbol": "COV",
            "Exchange": "HitBTC",
            "Blockchain": "Ethereum",
            "Address": "0xADA86b1b313D1D5267E3FC0bB303f0A2b66D0Ea7"
        },
        {
            "Symbol": "CPAY",
            "Exchange": "HitBTC",
            "Blockchain": "Ethereum",
            "Address": "0x0Ebb614204E47c09B6C3FeB9AAeCad8EE060E23E"
        },
        {
            "Symbol": "CPT",
            "Exchange": "HitBTC",
            "Blockchain": "Ethereum",
            "Address": "0x88d50B466BE55222019D71F9E8fAe17f5f45FCA1"
        },
        {
            "Symbol": "CRPT",
            "Exchange": "HitBTC",
            "Blockchain": "Ethereum",
            "Address": "0x08389495D7456E1951ddF7c3a1314A4bfb646d8B"
        },
        {
            "Symbol": "CVC",
            "Exchange": "HitBTC",
            "Blockchain": "Ethereum",
            "Address": "0x41e5560054824eA6B0732E656E3Ad64E20e94E45"
        },
        {
            "Symbol": "CVT",
            "Exchange": "HitBTC",
            "Blockchain": "Ethereum",
            "Address": "0xBe428c3867F05deA2A89Fc76a102b544eaC7f772"
        },
        {
            "Symbol": "DAI",
            "Exchange": "HitBTC",
            "Blockchain": "Ethereum",
            "Address": "0x6B175474E89094C44Da98b954EedeAC495271d0F"
        },
        {
            "Symbol": "DATA",
            "Exchange": "HitBTC",
            "Blockchain": "Ethereum",
            "Address": "0x0Cf0Ee63788A0849fE5297F3407f701E122cC023"
        },
        {
            "Symbol": "DATX",
            "Exchange": "HitBTC",
            "Blockchain": "Ethereum",
            "Address": "0xaBbBB6447B68ffD6141DA77C18c7B5876eD6c5ab"
        },
        {
            "Symbol": "DAY",
            "Exchange": "HitBTC",
            "Blockchain": "Ethereum",
            "Address": "0xE814aeE960a85208C3dB542C53E7D4a6C8D5f60F"
        },
        {
            "Symbol": "DCN",
            "Exchange": "HitBTC",
            "Blockchain": "Ethereum",
            "Address": "0x08d32b0da63e2C3bcF8019c9c5d849d7a9d791e6"
        },
        {
            "Symbol": "DENT",
            "Exchange": "HitBTC",
            "Blockchain": "Ethereum",
            "Address": "0x3597bfD533a99c9aa083587B074434E61Eb0A258"
        },
        {
            "Symbol": "DGD",
            "Exchange": "HitBTC",
            "Blockchain": "Ethereum",
            "Address": "0xE0B7927c4aF23765Cb51314A0E0521A9645F0E2A"
        },
        {
            "Symbol": "DGTX",
            "Exchange": "HitBTC",
            "Blockchain": "Ethereum",
            "Address": "0xc666081073E8DfF8D3d1c2292A29aE1A2153eC09"
        },
        {
            "Symbol": "DIT",
            "Exchange": "HitBTC",
            "Blockchain": "Ethereum",
            "Address": "0xf14922001A2FB8541a433905437ae954419C2439"
        },
        {
            "Symbol": "DLT",
            "Exchange": "HitBTC",
            "Blockchain": "Ethereum",
            "Address": "0x07e3c70653548B04f0A75970C1F81B4CBbFB606f"
        },
        {
            "Symbol": "DNT",
            "Exchange": "HitBTC",
            "Blockchain": "Ethereum",
            "Address": "0x0AbdAce70D3790235af448C88547603b945604ea"
        },
        {
            "Symbol": "DOT",
            "Exchange": "HitBTC",
            "Blockchain": "Polkadot",
            "Address": "0x0000000000000000000000000000000000000000"
        },
        {
            "Symbol": "DOV",
            "Exchange": "HitBTC",
            "Blockchain": "Ethereum",
            "Address": "0xac3211a5025414Af2866FF09c23FC18bc97e79b1"
        },
        {
            "Symbol": "DRG",
            "Exchange": "HitBTC",
            "Blockchain": "Ethereum",
            "Address": "0x814F67fA286f7572B041D041b1D99b432c9155Ee"
        },
        {
            "Symbol": "DRT",
            "Exchange": "HitBTC",
            "Blockchain": "Ethereum",
            "Address": "0x9AF4f26941677C706cfEcf6D3379FF01bB85D5Ab"
        },
        {
            "Symbol": "EKO",
            "Exchange": "HitBTC",
            "Blockchain": "Ethereum",
            "Address": "0xa6a840E50bCaa50dA017b91A0D86B8b2d41156EE"
        },
        {
            "Symbol": "ELEC",
            "Exchange": "HitBTC",
            "Blockchain": "Ethereum",
            "Address": "0xD49ff13661451313cA1553fd6954BD1d9b6E02b9"
        },
        {
            "Symbol": "ELF",
            "Exchange": "HitBTC",
            "Blockchain": "Ethereum",
            "Address": "0xbf2179859fc6D5BEE9Bf9158632Dc51678a4100e"
        },
        {
            "Symbol": "EMC",
            "Exchange": "HitBTC",
            "Blockchain": "Emercoin",
            "Address": "0x0000000000000000000000000000000000000000"
        },
        {
            "Symbol": "ERT",
            "Exchange": "HitBTC",
            "Blockchain": "Ethereum",
            "Address": "0xE29c5B523590165795BBD7d52369c2895B18841f"
        },
        {
            "Symbol": "ETN",
            "Exchange": "HitBTC",
            "Blockchain": "Electroneum",
            "Address": "0x0000000000000000000000000000000000000000"
        },
        {
            "Symbol": "ETP",
            "Exchange": "HitBTC",
            "Blockchain": "Metaverse",
            "Address": "0x0000000000000000000000000000000000000000"
        },
        {
            "Symbol": "EURS",
            "Exchange": "HitBTC",
            "Blockchain": "Ethereum",
            "Address": "0xdB25f211AB05b1c97D595516F45794528a807ad8"
        },
        {
            "Symbol": "FACE",
            "Exchange": "HitBTC",
            "Blockchain": "Ethereum",
            "Address": "0x1CCAA0F2a7210d76E1fDec740d5F323E2E1b1672"
        },
        {
            "Symbol": "FDZ",
            "Exchange": "HitBTC",
            "Blockchain": "Ethereum",
            "Address": "0x23352036E911A22Cfc692B5E2E196692658ADED9"
        },
        {
            "Symbol": "FIL",
            "Exchange": "HitBTC",
            "Blockchain": "Filecoin",
            "Address": "0x0000000000000000000000000000000000000000"
        },
        {
            "Symbol": "FLOW",
            "Exchange": "HitBTC",
            "Blockchain": "Flow",
            "Address": "0x0000000000000000000000000000000000000000"
        },
        {
            "Symbol": "FLP",
            "Exchange": "HitBTC",
            "Blockchain": "Ethereum",
            "Address": "0x3a1Bda28AdB5B0a812a7CF10A1950c920F79BcD3"
        },
        {
            "Symbol": "FOTA",
            "Exchange": "HitBTC",
            "Blockchain": "Ethereum",
            "Address": "0x4270bb238f6DD8B1c3ca01f96CA65b2647c06D3C"
        },
        {
            "Symbol": "FTM",
            "Exchange": "HitBTC",
            "Blockchain": "Fantom",
            "Address": "0x0000000000000000000000000000000000000000"
        },
        {
            "Symbol": "FTX",
            "Exchange": "HitBTC",
            "Blockchain": "Ethereum",
            "Address": "0xd559f20296FF4895da39b5bd9ADd54b442596a61"
        },
        {
            "Symbol": "FUN",
            "Exchange": "HitBTC",
            "Blockchain": "Ethereum",
            "Address": "0x419D0d8BdD9aF5e606Ae2232ed285Aff190E711b"
        },
        {
            "Symbol": "FXT",
            "Exchange": "HitBTC",
            "Blockchain": "Ethereum",
            "Address": "0x1829aA045E21E0D59580024A951DB48096e01782"
        },
        {
            "Symbol": "FYP",
            "Exchange": "HitBTC",
            "Blockchain": "Ethereum",
            "Address": "0x8F0921f30555624143d427b340b1156914882C10"
        },
        {
            "Symbol": "GBX",
            "Exchange": "HitBTC",
            "Blockchain": "GoByte",
            "Address": "0x0000000000000000000000000000000000000000"
        },
        {
            "Symbol": "GLM",
            "Exchange": "HitBTC",
            "Blockchain": "Ethereum",
            "Address": "0x7DD9c5Cba05E151C895FDe1CF355C9A1D5DA6429"
        },
        {
            "Symbol": "GNO",
            "Exchange": "HitBTC",
            "Blockchain": "Ethereum",
            "Address": "0x6810e776880C02933D47DB1b9fc05908e5386b96"
        },
        {
            "Symbol": "GNX",
            "Exchange": "HitBTC",
            "Blockchain": "Ethereum",
            "Address": "0x6EC8a24CaBdc339A06a172F8223ea557055aDAa5"
        },
        {
            "Symbol": "GUSD",
            "Exchange": "HitBTC",
            "Blockchain": "Ethereum",
            "Address": "0x056Fd409E1d7A124BD7017459dFEa2F387b6d5Cd"
        },
        {
            "Symbol": "GVT",
            "Exchange": "HitBTC",
            "Blockchain": "Ethereum",
            "Address": "0x103c3A209da59d3E7C4A89307e66521e081CFDF0"
        },
        {
            "Symbol": "HGT",
            "Exchange": "HitBTC",
            "Blockchain": "Ethereum",
            "Address": "0xba2184520A1cC49a6159c57e61E1844E085615B6"
        },
        {
            "Symbol": "HMQ",
            "Exchange": "HitBTC",
            "Blockchain": "Ethereum",
            "Address": "0xcbCC0F036ED4788F63FC0fEE32873d6A7487b908"
        },
        {
            "Symbol": "HVN",
            "Exchange": "HitBTC",
            "Blockchain": "Ethereum",
            "Address": "0xC0Eb85285d83217CD7c891702bcbC0FC401E2D9D"
        },
        {
            "Symbol": "IDH",
            "Exchange": "HitBTC",
            "Blockchain": "Ethereum",
            "Address": "0x5136C98A80811C3f46bDda8B5c4555CFd9f812F0"
        },
        {
            "Symbol": "IHT",
            "Exchange": "HitBTC",
            "Blockchain": "Ethereum",
            "Address": "0xEda8B016efA8b1161208Cf041cD86972eeE0F31E"
        },
        {
            "Symbol": "IND",
            "Exchange": "HitBTC",
            "Blockchain": "Ethereum",
            "Address": "0xf8e386EDa857484f5a12e4B5DAa9984E06E73705"
        },
        {
            "Symbol": "IPL",
            "Exchange": "HitBTC",
            "Blockchain": "Ethereum",
            "Address": "0x64CdF819d3E75Ac8eC217B3496d7cE167Be42e80"
        },
        {
            "Symbol": "KIN",
            "Exchange": "HitBTC",
            "Blockchain": "Solana",
            "Address": "kinXdEcpDQeHPEuQnqmUgtYykqKGVFq6CeVX5iAHJq6"
        },
        {
            "Symbol": "KIND",
            "Exchange": "HitBTC",
            "Blockchain": "Ethereum",
            "Address": "0x4618519de4C304F3444ffa7f812dddC2971cc688"
        },
        {
            "Symbol": "KSM",
            "Exchange": "HitBTC",
            "Blockchain": "Kusama",
            "Address": "0x0000000000000000000000000000000000000000"
        },
        {
            "Symbol": "LRC",
            "Exchange": "HitBTC",
            "Blockchain": "Ethereum",
            "Address": "0xBBbbCA6A901c926F240b89EacB641d8Aec7AEafD"
        },
        {
            "Symbol": "LSK",
            "Exchange": "HitBTC",
            "Blockchain": "Lisk",
            "Address": "0x0000000000000000000000000000000000000000"
        },
        {
            "Symbol": "LUN",
            "Exchange": "HitBTC",
            "Blockchain": "Ethereum",
            "Address": "0xfa05A73FfE78ef8f1a739473e462c54bae6567D9"
        },
        {
            "Symbol": "LUNA",
            "Exchange": "HitBTC",
            "Blockchain": "Terra",
            "Address": "0x0000000000000000000000000000000000000000"
        },
        {
            "Symbol": "MITX",
            "Exchange": "HitBTC",
            "Blockchain": "Ethereum",
            "Address": "0x4a527d8fc13C5203AB24BA0944F4Cb14658D1Db6"
        },
        {
            "Symbol": "MTH",
            "Exchange": "HitBTC",
            "Blockchain": "Ethereum",
            "Address": "0xaF4DcE16Da2877f8c9e00544c93B62Ac40631F16"
        },
        {
            "Symbol": "MTX",
            "Exchange": "HitBTC",
            "Blockchain": "Ethereum",
            "Address": "0x0AF44e2784637218dD1D32A322D44e603A8f0c6A"
        },
        {
            "Symbol": "MYST",
            "Exchange": "HitBTC",
            "Blockchain": "Ethereum",
            "Address": "0x4Cf89ca06ad997bC732Dc876ed2A7F26a9E7f361"
        },
        {
            "Symbol": "NANO",
            "Exchange": "HitBTC",
            "Blockchain": "Nano",
            "Address": "0x0000000000000000000000000000000000000000"
        },
        {
            "Symbol": "NCT",
            "Exchange": "HitBTC",
            "Blockchain": "Ethereum",
            "Address": "0x9E46A38F5DaaBe8683E10793b06749EEF7D733d1"
        },
        {
            "Symbol": "NEAR",
            "Exchange": "HitBTC",
            "Blockchain": "NEAR",
            "Address": "0x0000000000000000000000000000000000000000"
        },
        {
            "Symbol": "NEBL",
            "Exchange": "HitBTC",
            "Blockchain": "Neblio",
            "Address": "0x0000000000000000000000000000000000000000"
        },
        {
            "Symbol": "NEU",
            "Exchange": "HitBTC",
            "Blockchain": "Ethereum",
            "Address": "0xA823E6722006afe99E91c30FF5295052fe6b8E32"
        },
        {
            "Symbol": "NGC",
            "Exchange": "HitBTC",
            "Blockchain": "Ethereum",
            "Address": "0x72dD4b6bd852A3AA172Be4d6C5a6dbEc588cf131"
        },
        {
            "Symbol": "NIM",
            "Exchange": "HitBTC",
            "Blockchain": "Nimiq",
            "Address": "0x0000000000000000000000000000000000000000"
        },
        {
            "Symbol": "NMR",
            "Exchange": "HitBTC",
            "Blockchain": "Ethereum",
            "Address": "0x1776e1F26f98b1A5dF9cD347953a26dd3Cb46671"
        },
        {
            "Symbol": "OAX",
            "Exchange": "HitBTC",
            "Blockchain": "Ethereum",
            "Address": "0x701C244b988a513c945973dEFA05de933b23Fe1D"
        },
        {
            "Symbol": "OCN",
            "Exchange": "HitBTC",
            "Blockchain": "Ethereum",
            "Address": "0x4092678e4E78230F46A1534C0fbc8fA39780892B"
        },
        {
            "Symbol": "OPT",
            "Exchange": "HitBTC",
            "Blockchain": "Ethereum",
            "Address": "0x4355fC160f74328f9b383dF2EC589bB3dFd82Ba0"
        },
        {
            "Symbol": "PAY",
            "Exchange": "HitBTC",
            "Blockchain": "Ethereum",
            "Address": "0xB97048628DB6B661D4C2aA833e95Dbe1A905B280"
        },
        {
            "Symbol": "PAX",
            "Exchange": "HitBTC",
            "Blockchain": "Ethereum",
            "Address": "0x8E870D67F660D95d5be530380D0eC0bd388289E1"
        },
        {
            "Symbol": "PKT",
            "Exchange": "HitBTC",
            "Blockchain": "Ethereum",
            "Address": "0x2604FA406Be957E542BEb89E6754fCdE6815e83f"
        },
        {
            "Symbol": "PLBT",
            "Exchange": "HitBTC",
            "Blockchain": "Ethereum",
            "Address": "0x0AfFa06e7Fbe5bC9a764C979aA66E8256A631f02"
        },
        {
            "Symbol": "PLR",
            "Exchange": "HitBTC",
            "Blockchain": "Ethereum",
            "Address": "0xe3818504c1B32bF1557b16C238B2E01Fd3149C17"
        },
        {
            "Symbol": "PLU",
            "Exchange": "HitBTC",
            "Blockchain": "Ethereum",
            "Address": "0xD8912C10681D8B21Fd3742244f44658dBA12264E"
        },
        {
            "Symbol": "PMA",
            "Exchange": "HitBTC",
            "Blockchain": "Ethereum",
            "Address": "0x846C66cf71C43f80403B51fE3906B3599D63336f"
        },
        {
            "Symbol": "PNT",
            "Exchange": "HitBTC",
            "Blockchain": "Ethereum",
            "Address": "0x53066cdDBc0099eb6c96785d9b3DF2AAeEDE5DA3"
        },
        {
            "Symbol": "POE",
            "Exchange": "HitBTC",
            "Blockchain": "Ethereum",
            "Address": "0x0e0989b1f9B8A38983c2BA8053269Ca62Ec9B195"
        },
        {
            "Symbol": "PPC",
            "Exchange": "HitBTC",
            "Blockchain": "Peercoin",
            "Address": "0x0000000000000000000000000000000000000000"
        },
        {
            "Symbol": "PPT",
            "Exchange": "HitBTC",
            "Blockchain": "Ethereum",
            "Address": "0xd4fa1460F537bb9085d22C7bcCB5DD450Ef28e3a"
        },
        {
            "Symbol": "PRE",
            "Exchange": "HitBTC",
            "Blockchain": "Ethereum",
            "Address": "0xEC213F83defB583af3A000B1c0ada660b1902A0F"
        },
        {
            "Symbol": "PRO",
            "Exchange": "HitBTC",
            "Blockchain": "Ethereum",
            "Address": "0x226bb599a12C826476e3A771454697EA52E9E220"
        },
        {
            "Symbol": "PTOY",
            "Exchange": "HitBTC",
            "Blockchain": "Ethereum",
            "Address": "0x8Ae4BF2C33a8e667de34B54938B0ccD03Eb8CC06"
        },
        {
            "Symbol": "REP",
            "Exchange": "HitBTC",
            "Blockchain": "Ethereum",
            "Address": "0x221657776846890989a759BA2973e427DfF5C9bB"
        },
        {
            "Symbol": "REX",
            "Exchange": "HitBTC",
            "Blockchain": "Ethereum",
            "Address": "0xf05a9382A4C3F29E2784502754293D88b835109C"
        },
        {
            "Symbol": "RLC",
            "Exchange": "HitBTC",
            "Blockchain": "Ethereum",
            "Address": "0x607F4C5BB672230e8672085532f7e901544a7375"
        },
        {
            "Symbol": "SCL",
            "Exchange": "HitBTC",
            "Blockchain": "Ethereum",
            "Address": "0xd7631787B4dCc87b1254cfd1e5cE48e96823dEe8"
        },
        {
            "Symbol": "SHIP",
            "Exchange": "HitBTC",
            "Blockchain": "Ethereum",
            "Address": "0xe25b0BBA01Dc5630312B6A21927E578061A13f55"
        },
        {
            "Symbol": "SIG",
            "Exchange": "HitBTC",
            "Blockchain": "Ethereum",
            "Address": "0x6888a16eA9792c15A4DCF2f6C623D055c8eDe792"
        },
        {
            "Symbol": "SMART",
            "Exchange": "HitBTC",
            "Blockchain": "SmartCash",
            "Address": "0x0000000000000000000000000000000000000000"
        },
        {
            "Symbol": "SNC",
            "Exchange": "HitBTC",
            "Blockchain": "Ethereum",
            "Address": "0xF4134146AF2d511Dd5EA8cDB1C4AC88C57D60404"
        },
        {
            "Symbol": "SNGLS",
            "Exchange": "HitBTC",
            "Blockchain": "Ethereum",
            "Address": "0xaeC2E87E0A235266D9C5ADc9DEb4b2E29b54D009"
        },
        {
            "Symbol": "SNT",
            "Exchange": "HitBTC",
            "Blockchain": "Ethereum",
            "Address": "0x744d70FDBE2Ba4CF95131626614a1763DF805B9E"
        },
        {
            "Symbol": "SOC",
            "Exchange": "HitBTC",
            "Blockchain": "Ethereum",
            "Address": "0x2d0E95bd4795D7aCe0da3C0Ff7b706a5970eb9D3"
        },
        {
            "Symbol": "SPC",
            "Exchange": "HitBTC",
            "Blockchain": "Ethereum",
            "Address": "0x86ed939B500E121C0C5f493F399084Db596dAd20"
        },
        {
            "Symbol": "SRN",
            "Exchange": "HitBTC",
            "Blockchain": "Ethereum",
            "Address": "0x68d57c9a1C35f63E2c83eE8e49A64e9d70528D25"
        },
        {
            "Symbol": "STAK",
            "Exchange": "HitBTC",
            "Blockchain": "Ethereum",
            "Address": "0x1F8A626883d7724DBd59eF51CBD4BF1Cf2016D13"
        },
        {
            "Symbol": "STRAT",
            "Exchange": "HitBTC",
            "Blockchain": "Stratis",
            "Address": "0x0000000000000000000000000000000000000000"
        },
        {
            "Symbol": "SUB",
            "Exchange": "HitBTC",
            "Blockchain": "Ethereum",
            "Address": "0x8D75959f1E61EC2571aa72798237101F084DE63a"
        },
        {
            "Symbol": "SUR",
            "Exchange": "HitBTC",
            "Blockchain": "Ethereum",
            "Address": "0xe120c1ECBfdFeA7F0A8f0Ee30063491E8c26fedf"
        },
        {
            "Symbol": "SWFTC",
            "Exchange": "HitBTC",
            "Blockchain": "Ethereum",
            "Address": "0x0bb217E40F8a5Cb79Adf04E1aAb60E5abd0dfC1e"
        },
        {
            "Symbol": "SWM",
            "Exchange": "HitBTC",
            "Blockchain": "Ethereum",
            "Address": "0x3505F494c3f0fed0B594E01Fa41Dd3967645ca39"
        },
        {
            "Symbol": "SWT",
            "Exchange": "HitBTC",
            "Blockchain": "Ethereum",
            "Address": "0xB9e7F8568e08d5659f5D29C4997173d84CdF2607"
        },
        {
            "Symbol": "TIME",
            "Exchange": "HitBTC",
            "Blockchain": "Ethereum",
            "Address": "0x485d17A6f1B8780392d53D64751824253011A260"
        },
        {
            "Symbol": "TKN",
            "Exchange": "HitBTC",
            "Blockchain": "Ethereum",
            "Address": "0xaAAf91D9b90dF800Df4F55c205fd6989c977E73a"
        },
        {
            "Symbol": "TRST",
            "Exchange": "HitBTC",
            "Blockchain": "Ethereum",
            "Address": "0xCb94be6f13A1182E4A4B6140cb7bf2025d28e41B"
        },
        {
            "Symbol": "TRUE",
            "Exchange": "HitBTC",
            "Blockchain": "TrueChain",
            "Address": "0x0000000000000000000000000000000000000000"
        },
        {
            "Symbol": "TV",
            "Exchange": "HitBTC",
            "Blockchain": "Ethereum",
            "Address": "0xF3E693175Db47264c99ECa0F1C1C4A2C1AeD3Bd7"
        },
        {
            "Symbol": "USD",
            "Exchange": "HitBTC",
            "Blockchain": "Fiat",
            "Address": "840"
        },
        {
            "Symbol": "USDC",
            "Exchange": "HitBTC",
            "Blockchain": "Ethereum",
            "Address": "0xA0b86991c6218b36c1d19D4a2e9Eb0cE3606eB48"
        },
        {
            "Symbol": "USE",
            "Exchange": "HitBTC",
            "Blockchain": "Ethereum",
            "Address": "0xd9485499499d66B175Cf5ED54c0a19f1a6Bcb61A"
        },
        {
            "Symbol": "UTK",
            "Exchange": "HitBTC",
            "Blockchain": "Ethereum",
            "Address": "0xdc9Ac3C20D1ed0B540dF9b1feDC10039Df13F99c"
        },
        {
            "Symbol": "UTT",
            "Exchange": "HitBTC",
            "Blockchain": "Ethereum",
            "Address": "0x16f812Be7FfF02cAF662B85d5d58a5da6572D4Df"
        },
        {
            "Symbol": "UUU",
            "Exchange": "HitBTC",
            "Blockchain": "Ethereum",
            "Address": "0x3543638eD4a9006E4840B105944271Bcea15605D"
        },
        {
            "Symbol": "VIB",
            "Exchange": "HitBTC",
            "Blockchain": "Ethereum",
            "Address": "0x2C974B2d0BA1716E644c1FC59982a89DDD2fF724"
        },
        {
            "Symbol": "VIBE",
            "Exchange": "HitBTC",
            "Blockchain": "Ethereum",
            "Address": "0xe8Ff5C9c75dEb346acAc493C463C8950Be03Dfba"
        },
        {
            "Symbol": "WIKI",
            "Exchange": "HitBTC",
            "Blockchain": "Ethereum",
            "Address": "0x66BaD545596fb17a0B4ebDC003a85dEF10E8F6Ae"
        },
        {
            "Symbol": "WINGS",
            "Exchange": "HitBTC",
            "Blockchain": "Ethereum",
            "Address": "0x667088b212ce3d06a1b553a7221E1fD19000d9aF"
        },
        {
            "Symbol": "XAUR",
            "Exchange": "HitBTC",
            "Blockchain": "Ethereum",
            "Address": "0x4DF812F6064def1e5e029f1ca858777CC98D2D81"
        },
        {
            "Symbol": "XBP",
            "Exchange": "HitBTC",
            "Blockchain": "Ethereum",
            "Address": "0x28dee01D53FED0Edf5f6E310BF8Ef9311513Ae40"
        },
        {
            "Symbol": "XDN",
            "Exchange": "HitBTC",
            "Blockchain": "DigitalNote",
            "Address": "0x0000000000000000000000000000000000000000"
        },
        {
            "Symbol": "XMR",
            "Exchange": "HitBTC",
            "Blockchain": "Monero",
            "Address": "0x0000000000000000000000000000000000000000"
        },
        {
            "Symbol": "XUC",
            "Exchange": "HitBTC",
            "Blockchain": "Ethereum",
            "Address": "0xc324a2f6b05880503444451B8b27e6f9e63287Cb"
        },
        {
            "Symbol": "XVG",
            "Exchange": "HitBTC",
            "Blockchain": "Verge",
            "Address": "0x0000000000000000000000000000000000000000"
        },
        {
            "Symbol": "YGG",
            "Exchange": "HitBTC",
            "Blockchain": "Ethereum",
            "Address": "0x25f8087EAD173b73D6e8B84329989A8eEA16CF73"
        },
        {
            "Symbol": "YCC",
            "Exchange": "HitBTC",
            "Blockchain": "Ethereum",
            "Address": "0x37E1160184F7dD29f00b78C050Bf13224780b0B0"
        },
        {
            "Symbol": "ZAP",
            "Exchange": "HitBTC",
            "Blockchain": "Ethereum",
            "Address": "0x6781a0F84c7E9e846DCb84A9a5bd49333067b104"
        },
        {
            "Symbol": "ZSC",
            "Exchange": "HitBTC",
            "Blockchain": "Ethereum",
            "Address": "0x7A41e0517a5ecA4FdbC7FbebA4D4c47B9fF6DC63"
        }
    ]
}