{
    "Tokens": [
        {
            "Symbol": "ACA",
            "Exchange": "KuCoin",
            "Blockchain": "Acala",
            "Address": "Token:ACA"
        },
        {
            "Symbol": "ADB",
            "Exchange": "KuCoin",
            "Blockchain": "Ethereum",
            "Address": "0x2baac9330Cf9aC479D819195794d79AD0c7616e3"
        },
        {
            "Symbol": "AERGO",
            "Exchange": "KuCoin",
            "Blockchain": "Ethereum",
            "Address": "0x91Af0fBB28ABA7E31403Cb457106Ce79397FD4E6"
        },
        {
            "Symbol": "AKRO",
            "Exchange": "KuCoin",
            "Blockchain": "Ethereum",
            "Address": "0x8Ab7404063Ec4DBcfd4598215992DC3F8EC853d7"
        },
        {
            "Symbol": "ALEPH",
            "Exchange": "KuCoin",
            "Blockchain": "Ethereum",
            "Address": "0x27702a26126e0B3702af63Ee09aC4d1A084EF628"
        },
        {
            "Symbol": "AMPL",
            "Exchange": "KuCoin",
            "Blockchain": "Ethereum",
            "Address": "0xD46bA6D942050d489DBd938a2C909A5d5039A161"
        },
        {
            "Symbol": "ANKR",
            "Exchange": "KuCoin",
            "Blockchain": "Ethereum",
            "Address": "0x8290333ceF9e6D528dD5618Fb97a76f268f3EDD4"
        },
        {
            "Symbol": "ANT",
            "Exchange": "KuCoin",
            "Blockchain": "Ethereum",
            "Address": "0xa117000000f279D81A1D3cc75430fAA017FA5A2e"
        },
        {
            "Symbol": "AOA",
            "Exchange": "KuCoin",
            "Blockchain": "Ethereum",
            "Address": "0x9ab165D795019b6d8B3e971DdA91071421305e5a"
        },
        {
            "Symbol": "API3",
            "Exchange": "KuCoin",
            "Blockchain": "Ethereum",
            "Address": "0x0b38210ea11411557c13457D4dA7dC6ea731B88a"
        },
        {
            "Symbol": "ASTR",
            "Exchange": "KuCoin",
            "Blockchain": "Astar",
            "Address": "0x0000000000000000000000000000000000000000"
        },
        {
            "Symbol": "AUSD",
            "Exchange": "KuCoin",
            "Blockchain": "Acala",
            "Address": "Token:AUSD"
        },
        {
            "Symbol": "BCHSV",
            "Exchange": "KuCoin",
            "Blockchain": "BitcoinSV",
            "Address": "0x0000000000000000000000000000000000000000"
        },
        {
            "Symbol": "BNB",
            "Exchange": "KuCoin",
            "Blockchain": "BinanceSmartChain",
            "Address": "0x0000000000000000000000000000000000000000"
        },
        {
            "Symbol": "BOLT",
            "Exchange": "KuCoin",
            "Blockchain": "Ethereum",
            "Address": "0xD5930C307d7395Ff807F2921F12C5EB82131a789"
        },
        {
            "Symbol": "BOSON",
            "Exchange": "KuCoin",
            "Blockchain": "Ethereum",
            "Address": "0xC477D038d5420C6A9e0b031712f61c5120090de9"
        },
        {
            "Symbol": "BUY",
            "Exchange": "KuCoin",
            "Blockchain": "Ethereum",
            "Address": "0x31Fdd1c6607F47C14a2821f599211c67AC20FA96"
        },
        {
            "Symbol": "CAPP",
            "Exchange": "KuCoin",
            "Blockchain": "Ethereum",
            "Address": "0x04F2E7221fdb1B52A68169B25793E51478fF0329"
        },
        {
            "Symbol": "CARD",
            "Exchange": "KuCoin",
            "Blockchain": "Ethereum",
            "Address": "0x954b890704693af242613edEf1B603825afcD708"
        },
        {
            "Symbol": "CBC",
            "Exchange": "KuCoin",
            "Blockchain": "Ethereum",
            "Address": "0x26DB5439F651CAF491A87d48799dA81F191bDB6b"
        },
        {
            "Symbol": "CHR",
            "Exchange": "KuCoin",
            "Blockchain": "Ethereum",
            "Address": "0x8A2279d4A90B6fe1C4B30fa660cC9f926797bAA2"
        },
        {
            "Symbol": "CIX100",
            "Exchange": "KuCoin",
            "Blockchain": "Ethereum",
            "Address": "0x6393E822874728f8Afa7e1C9944E417D37CA5878"
        },
        {
            "Symbol": "COFI",
            "Exchange": "KuCoin",
            "Blockchain": "Ethereum",
            "Address": "0x3136eF851592aCf49CA4C825131E364170FA32b3"
        },
        {
            "Symbol": "CSP",
            "Exchange": "KuCoin",
            "Blockchain": "Ethereum",
            "Address": "0xA6446D655a0c34bC4F05042EE88170D056CBAf45"
        },
        {
            "Symbol": "CTI",
            "Exchange": "KuCoin",
            "Blockchain": "Ethereum",
            "Address": "0x8c18D6a985Ef69744b9d57248a45c0861874f244"
        },
        {
            "Symbol": "CUDOS",
            "Exchange": "KuCoin",
            "Blockchain": "Ethereum",
            "Address": "0x817bbDbC3e8A1204f3691d14bB44992841e3dB35"
        },
        {
            "Symbol": "CUSD",
            "Exchange": "KuCoin",
            "Blockchain": "Celo",
            "Address": "0x765DE816845861e75A25fCA122bb6898B8B1282a"
        },
        {
            "Symbol": "CVC",
            "Exchange": "KuCoin",
            "Blockchain": "Ethereum",
            "Address": "0x41e5560054824eA6B0732E656E3Ad64E20e94E45"
        },
        {
            "Symbol": "CXO",
            "Exchange": "KuCoin",
            "Blockchain": "Ethereum",
            "Address": "0xb6EE9668771a79be7967ee29a63D4184F8097143"
        },
        {
            "Symbol": "DATX",
            "Exchange": "KuCoin",
            "Blockchain": "Ethereum",
            "Address": "0xaBbBB6447B68ffD6141DA77C18c7B5876eD6c5ab"
        },
        {
            "Symbol": "DEGO",
            "Exchange": "KuCoin",
            "Blockchain": "Ethereum",
            "Address": "0x88EF27e69108B2633F8E1C184CC37940A075cC02"
        },
        {
            "Symbol": "DENT",
            "Exchange": "KuCoin",
            "Blockchain": "Ethereum",
            "Address": "0x3597bfD533a99c9aa083587B074434E61Eb0A258"
        },
        {
            "Symbol": "DFYN",
            "Exchange": "KuCoin",
            "Blockchain": "Polygon",
            "Address": "0xC168E40227E4ebD8C1caE80F7a55a4F0e6D66C97"
        },
        {
            "Symbol": "DMG",
            "Exchange": "KuCoin",
            "Blockchain": "Ethereum",
            "Address": "0xEd91879919B71bB6905f23af0A68d231EcF87b14"
        },
        {
            "Symbol": "DODO",
            "Exchange": "KuCoin",
            "Blockchain": "Ethereum",
            "Address": "0x43Dfc4159D86F3A37A5A4B3D4580b888ad7d4DDd"
        },
        {
            "Symbol": "DRGN",
            "Exchange": "KuCoin",
            "Blockchain": "Ethereum",
            "Address": "0x419c4dB4B9e25d6Db2AD9691ccb832C8D9fDA05E"
        },
        {
            "Symbol": "DSLA",
            "Exchange": "KuCoin",
            "Blockchain": "Ethereum",
            "Address": "0x3aFfCCa64c2A6f4e3B6Bd9c64CD2C969EFd1ECBe"
        },
        {
            "Symbol": "DX",
            "Exchange": "KuCoin",
            "Blockchain": "Ethereum",
            "Address": "0x973e52691176d36453868D9d86572788d27041A9"
        },
        {
            "Symbol": "DYP",
            "Exchange": "KuCoin",
            "Blockchain": "Ethereum",
            "Address": "0x961C8c0B1aaD0c0b10a51FeF6a867E3091BCef17"
        },
        {
            "Symbol": "EDN",
            "Exchange": "KuCoin",
            "Blockchain": "Ethereum",
            "Address": "0x89020f0D5C5AF4f3407Eb5Fe185416c457B0e93e"
        },
        {
            "Symbol": "ELF",
            "Exchange": "KuCoin",
            "Blockchain": "Ethereum",
            "Address": "0xbf2179859fc6D5BEE9Bf9158632Dc51678a4100e"
        },
        {
            "Symbol": "FET",
            "Exchange": "KuCoin",
            "Blockchain": "Fetch",
            "Address": "0x0000000000000000000000000000000000000000"
        },
        {
            "Symbol": "FLOW",
            "Exchange": "KuCoin",
            "Blockchain": "Flow",
            "Address": "0x0000000000000000000000000000000000000000"
        },
        {
            "Symbol": "FRM",
            "Exchange": "KuCoin",
            "Blockchain": "Ethereum",
            "Address": "0xE5CAeF4Af8780E59Df925470b050Fb23C43CA68C"
        },
        {
            "Symbol": "FRONT",
            "Exchange": "KuCoin",
            "Blockchain": "Ethereum",
            "Address": "0xf8C3527CC04340b208C854E985240c02F7B7793f"
        },
        {
            "Symbol": "FTM",
            "Exchange": "KuCoin",
            "Blockchain": "Fantom",
            "Address": "0x0000000000000000000000000000000000000000"
        },
        {
            "Symbol": "GHST",
            "Exchange": "KuCoin",
            "Blockchain": "Ethereum",
            "Address": "0x3F382DbD960E3a9bbCeaE22651E88158d2791550"
        },
        {
            "Symbol": "GLMR",
            "Exchange": "KuCoin",
            "Blockchain": "Moonbeam",
            "Address": "0x0000000000000000000000000000000000000000"
        },
        {
            "Symbol": "GMB",
            "Exchange": "KuCoin",
            "Blockchain": "Ethereum",
            "Address": "0xA0008F510fE9eE696E7E320C9e5cbf61E27791Ee"
        },
        {
            "Symbol": "KAT",
            "Exchange": "KuCoin",
            "Blockchain": "Ethereum",
            "Address": "0x14da230d6726C50F759Bc1838717F8CE6373509C"
        },
        {
            "Symbol": "KEY",
            "Exchange": "KuCoin",
            "Blockchain": "Ethereum",
            "Address": "0x4CC19356f2D37338b9802aa8E8fc58B0373296E7"
        },
        {
            "Symbol": "KSM",
            "Exchange": "KuCoin",
            "Blockchain": "Kusama",
            "Address": "0x0000000000000000000000000000000000000000"
        },
        {
            "Symbol": "LAYER",
            "Exchange": "KuCoin",
            "Blockchain": "Ethereum",
            "Address": "0x0fF6ffcFDa92c53F615a4A75D982f399C989366b"
        },
        {
            "Symbol": "LON",
            "Exchange": "KuCoin",
            "Blockchain": "Ethereum",
            "Address": "0x0000000000095413afC295d19EDeb1Ad7B71c952"
        },
        {
            "Symbol": "LRC",
            "Exchange": "KuCoin",
            "Blockchain": "Ethereum",
            "Address": "0xBBbbCA6A901c926F240b89EacB641d8Aec7AEafD"
        }
    ]
}